intentionet/bfe/proto/api_gateway_pb2.py
intentionet/bfe/proto/api_gateway_pb2.pyi
intentionet/bfe/proto/api_gateway_pb2_grpc.py
intentionet/bfe/proto/assertions/adhoc_pb2.py
intentionet/bfe/proto/assertions/adhoc_pb2.pyi
intentionet/bfe/proto/assertions/bgp_pb2.py
intentionet/bfe/proto/assertions/bgp_pb2.pyi
intentionet/bfe/proto/assertions/core_pb2.py
intentionet/bfe/proto/assertions/core_pb2.pyi
intentionet/bfe/proto/assertions/filters_pb2.py
intentionet/bfe/proto/assertions/filters_pb2.pyi
intentionet/bfe/proto/assertions/flow_pb2.py
intentionet/bfe/proto/assertions/flow_pb2.pyi
intentionet/bfe/proto/assertions/insights_pb2.py
intentionet/bfe/proto/assertions/insights_pb2.pyi
intentionet/bfe/proto/assertions/interfaces_pb2.py
intentionet/bfe/proto/assertions/interfaces_pb2.pyi
intentionet/bfe/proto/assertions/isis_pb2.py
intentionet/bfe/proto/assertions/isis_pb2.pyi
intentionet/bfe/proto/assertions/mlag_pb2.py
intentionet/bfe/proto/assertions/mlag_pb2.pyi
intentionet/bfe/proto/assertions/ospf_pb2.py
intentionet/bfe/proto/assertions/ospf_pb2.pyi
intentionet/bfe/proto/assertions/parameters_pb2.py
intentionet/bfe/proto/assertions/parameters_pb2.pyi
intentionet/bfe/proto/assertions/reachability_pb2.py
intentionet/bfe/proto/assertions/reachability_pb2.pyi
intentionet/bfe/proto/assertions/reference_pb2.py
intentionet/bfe/proto/assertions/reference_pb2.pyi
intentionet/bfe/proto/assertions/route_pb2.py
intentionet/bfe/proto/assertions/route_pb2.pyi
intentionet/bfe/proto/assertions/snmp_pb2.py
intentionet/bfe/proto/assertions/snmp_pb2.pyi
intentionet/bfe/proto/assertions/text_pb2.py
intentionet/bfe/proto/assertions/text_pb2.pyi
intentionet/bfe/proto/assertions/traceroute_pb2.py
intentionet/bfe/proto/assertions/traceroute_pb2.pyi
intentionet/bfe/proto/assertions/violations_pb2.py
intentionet/bfe/proto/assertions/violations_pb2.pyi
intentionet/bfe/proto/auth/auth_pb2.py
intentionet/bfe/proto/auth/auth_pb2.pyi
intentionet/bfe/proto/auth/credentials_pb2.py
pybfe-2022.07.25.2966.dist-info/METADATA
pybfe-2022.07.25.2966.dist-info/RECORD
pybfe-2022.07.25.2966.dist-info/WHEEL
pybfe-2022.07.25.2966.dist-info/entry_points.txt
