Metadata-Version: 2.1
Name: pybfe
Version: 2022.07.25.2966
License: Proprietary, included with Pybatfish Enterprise at pybfe/LICENSE
Classifier: Programming Language :: Python :: 3
Classifier: Programming Language :: Python :: 3 :: Only
Classifier: Programming Language :: Python :: 3.7
Classifier: Programming Language :: Python :: 3.8
Classifier: Programming Language :: Python :: 3.9
Requires-Python: >=3.7
Requires-Dist: cryptography<4
Requires-Dist: grpcio>=1.43,<1.44
Requires-Dist: pandas<1.2
Requires-Dist: protobuf>=3.19,<3.20
Requires-Dist: pybatfish>=2022.02.18.1216
Requires-Dist: pytz
Requires-Dist: requests<3
Provides-Extra: capirca
Requires-Dist: pybatfish[capirca]>=2021.7.9.974; extra == 'capirca'
